[
  {
    "name": "Chinese Simplified",
    "code": "zh-CN",
    "phrases": "14506",
    "translated": "8544",
    "approved": "8156",
    "words": "157783",
    "words_translated": "85511",
    "words_approved": "81259",
    "translated_progress": 54,
    "approved_progress": 51,
    "qa_issues": 14
  },
  {
    "name": "French",
    "code": "fr",
    "phrases": "14506",
    "translated": "8352",
    "approved": "8058",
    "words": "157783",
    "words_translated": "78050",
    "words_approved": "75731",
    "translated_progress": 49,
    "approved_progress": 47,
    "qa_issues": 95
  },
  {
    "name": "German",
    "code": "de",
    "phrases": "14506",
    "translated": "3358",
    "approved": "3292",
    "words": "157783",
    "words_translated": "23794",
    "words_approved": "23218",
    "translated_progress": 15,
    "approved_progress": 14,
    "qa_issues": 31
  },
  {
    "name": "Japanese",
    "code": "ja",
    "phrases": "14506",
    "translated": "14506",
    "approved": "14223",
    "words": "157783",
    "words_translated": "157783",
    "words_approved": "154354",
    "translated_progress": 100,
    "approved_progress": 97,
    "qa_issues": 11
  },
  {
    "name": "Portuguese, Brazilian",
    "code": "pt-BR",
    "phrases": "14506",
    "translated": "3557",
    "approved": "3540",
    "words": "157783",
    "words_translated": "29874",
    "words_approved": "29721",
    "translated_progress": 18,
    "approved_progress": 18,
    "qa_issues": 5
  },
  {
    "name": "Russian",
    "code": "ru",
    "phrases": "14506",
    "translated": "6353",
    "approved": "6226",
    "words": "157783",
    "words_translated": "57919",
    "words_approved": "56125",
    "translated_progress": 36,
    "approved_progress": 35,
    "qa_issues": 50
  },
  {
    "name": "Spanish",
    "code": "es-ES",
    "phrases": "14506",
    "translated": "9626",
    "approved": "9554",
    "words": "157783",
    "words_translated": "95243",
    "words_approved": "94735",
    "translated_progress": 60,
    "approved_progress": 60,
    "qa_issues": 19
  }
]