[
  {
    "name": "Arabic",
    "code": "ar",
    "phrases": "10619",
    "translated": "1260",
    "approved": "1",
    "words": "97719",
    "words_translated": "7970",
    "words_approved": "2",
    "translated_progress": 8,
    "approved_progress": 0,
    "qa_issues": 454
  },
  {
    "name": "Bulgarian",
    "code": "bg",
    "phrases": "10619",
    "translated": "2491",
    "approved": "3",
    "words": "97719",
    "words_translated": "13396",
    "words_approved": "6",
    "translated_progress": 13,
    "approved_progress": 0,
    "qa_issues": 692
  },
  {
    "name": "Chinese Simplified",
    "code": "zh-CN",
    "phrases": "10619",
    "translated": "8854",
    "approved": "24",
    "words": "97719",
    "words_translated": "76393",
    "words_approved": "96",
    "translated_progress": 78,
    "approved_progress": 0,
    "qa_issues": 247
  },
  {
    "name": "Chinese Traditional",
    "code": "zh-TW",
    "phrases": "10619",
    "translated": "4627",
    "approved": "46",
    "words": "97719",
    "words_translated": "22768",
    "words_approved": "115",
    "translated_progress": 23,
    "approved_progress": 0,
    "qa_issues": 58
  },
  {
    "name": "Czech",
    "code": "cs",
    "phrases": "10619",
    "translated": "1232",
    "approved": "0",
    "words": "97719",
    "words_translated": "3370",
    "words_approved": "0",
    "translated_progress": 3,
    "approved_progress": 0,
    "qa_issues": 255
  },
  {
    "name": "Dutch",
    "code": "nl",
    "phrases": "10619",
    "translated": "2882",
    "approved": "2",
    "words": "97719",
    "words_translated": "11075",
    "words_approved": "19",
    "translated_progress": 11,
    "approved_progress": 0,
    "qa_issues": 827
  },
  {
    "name": "Filipino",
    "code": "fil",
    "phrases": "10619",
    "translated": "7657",
    "approved": "965",
    "words": "97719",
    "words_translated": "61466",
    "words_approved": "9685",
    "translated_progress": 62,
    "approved_progress": 9,
    "qa_issues": 209
  },
  {
    "name": "French",
    "code": "fr",
    "phrases": "10619",
    "translated": "7449",
    "approved": "39",
    "words": "97719",
    "words_translated": "55578",
    "words_approved": "142",
    "translated_progress": 56,
    "approved_progress": 0,
    "qa_issues": 2143
  },
  {
    "name": "German",
    "code": "de",
    "phrases": "10619",
    "translated": "4697",
    "approved": "34",
    "words": "97719",
    "words_translated": "27059",
    "words_approved": "65",
    "translated_progress": 27,
    "approved_progress": 0,
    "qa_issues": 1828
  },
  {
    "name": "Hebrew",
    "code": "he",
    "phrases": "10619",
    "translated": "476",
    "approved": "0",
    "words": "97719",
    "words_translated": "3087",
    "words_approved": "0",
    "translated_progress": 3,
    "approved_progress": 0,
    "qa_issues": 125
  },
  {
    "name": "Hindi",
    "code": "hi",
    "phrases": "10619",
    "translated": "1451",
    "approved": "6",
    "words": "97719",
    "words_translated": "13912",
    "words_approved": "28",
    "translated_progress": 14,
    "approved_progress": 0,
    "qa_issues": 1344
  },
  {
    "name": "Indonesian",
    "code": "id",
    "phrases": "10619",
    "translated": "7726",
    "approved": "4",
    "words": "97719",
    "words_translated": "62050",
    "words_approved": "20",
    "translated_progress": 63,
    "approved_progress": 0,
    "qa_issues": 4134
  },
  {
    "name": "Italian",
    "code": "it",
    "phrases": "10619",
    "translated": "4781",
    "approved": "1",
    "words": "97719",
    "words_translated": "33980",
    "words_approved": "1",
    "translated_progress": 34,
    "approved_progress": 0,
    "qa_issues": 1732
  },
  {
    "name": "Japanese",
    "code": "ja",
    "phrases": "10619",
    "translated": "10563",
    "approved": "289",
    "words": "97719",
    "words_translated": "97053",
    "words_approved": "1692",
    "translated_progress": 99,
    "approved_progress": 1,
    "qa_issues": 317
  },
  {
    "name": "Korean",
    "code": "ko",
    "phrases": "10619",
    "translated": "4936",
    "approved": "465",
    "words": "97719",
    "words_translated": "41860",
    "words_approved": "4647",
    "translated_progress": 42,
    "approved_progress": 4,
    "qa_issues": 2189
  },
  {
    "name": "Persian",
    "code": "fa",
    "phrases": "10619",
    "translated": "1085",
    "approved": "29",
    "words": "97719",
    "words_translated": "4685",
    "words_approved": "53",
    "translated_progress": 4,
    "approved_progress": 0,
    "qa_issues": 29
  },
  {
    "name": "Polish",
    "code": "pl",
    "phrases": "10619",
    "translated": "4421",
    "approved": "1022",
    "words": "97719",
    "words_translated": "21760",
    "words_approved": "6774",
    "translated_progress": 22,
    "approved_progress": 6,
    "qa_issues": 936
  },
  {
    "name": "Portuguese, Brazilian",
    "code": "pt-BR",
    "phrases": "10619",
    "translated": "4632",
    "approved": "359",
    "words": "97719",
    "words_translated": "33055",
    "words_approved": "2585",
    "translated_progress": 33,
    "approved_progress": 2,
    "qa_issues": 1330
  },
  {
    "name": "Romanian",
    "code": "ro",
    "phrases": "10619",
    "translated": "428",
    "approved": "0",
    "words": "97719",
    "words_translated": "1893",
    "words_approved": "0",
    "translated_progress": 1,
    "approved_progress": 0,
    "qa_issues": 98
  },
  {
    "name": "Russian",
    "code": "ru",
    "phrases": "10619",
    "translated": "6609",
    "approved": "2628",
    "words": "97719",
    "words_translated": "51401",
    "words_approved": "22010",
    "translated_progress": 52,
    "approved_progress": 22,
    "qa_issues": 1420
  },
  {
    "name": "Spanish",
    "code": "es-ES",
    "phrases": "10619",
    "translated": "9308",
    "approved": "252",
    "words": "97719",
    "words_translated": "77501",
    "words_approved": "2018",
    "translated_progress": 79,
    "approved_progress": 2,
    "qa_issues": 3590
  },
  {
    "name": "Tagalog",
    "code": "tl",
    "phrases": "10619",
    "translated": "2",
    "approved": "0",
    "words": "97719",
    "words_translated": "11",
    "words_approved": "0",
    "translated_progress": 0,
    "approved_progress": 0,
    "qa_issues": 0
  },
  {
    "name": "Thai",
    "code": "th",
    "phrases": "10619",
    "translated": "1369",
    "approved": "3",
    "words": "97719",
    "words_translated": "7554",
    "words_approved": "20",
    "translated_progress": 7,
    "approved_progress": 0,
    "qa_issues": 626
  },
  {
    "name": "Turkish",
    "code": "tr",
    "phrases": "10619",
    "translated": "7869",
    "approved": "1",
    "words": "97719",
    "words_translated": "63396",
    "words_approved": "1",
    "translated_progress": 64,
    "approved_progress": 0,
    "qa_issues": 3632
  },
  {
    "name": "Ukrainian",
    "code": "uk",
    "phrases": "10619",
    "translated": "4037",
    "approved": "150",
    "words": "97719",
    "words_translated": "24025",
    "words_approved": "665",
    "translated_progress": 24,
    "approved_progress": 0,
    "qa_issues": 1592
  },
  {
    "name": "Vietnamese",
    "code": "vi",
    "phrases": "10619",
    "translated": "1995",
    "approved": "50",
    "words": "97719",
    "words_translated": "9305",
    "words_approved": "124",
    "translated_progress": 9,
    "approved_progress": 0,
    "qa_issues": 547
  }
]