[
  {
    "name": "Arabic",
    "code": "ar",
    "phrases": "9953",
    "translated": "993",
    "approved": "0",
    "words": "92100",
    "words_translated": "6407",
    "words_approved": "0",
    "translated_progress": 6,
    "approved_progress": 0,
    "qa_issues": 369
  },
  {
    "name": "Bulgarian",
    "code": "bg",
    "phrases": "9953",
    "translated": "2435",
    "approved": "3",
    "words": "92100",
    "words_translated": "13590",
    "words_approved": "6",
    "translated_progress": 14,
    "approved_progress": 0,
    "qa_issues": 701
  },
  {
    "name": "Chinese Simplified",
    "code": "zh-CN",
    "phrases": "9953",
    "translated": "8653",
    "approved": "26",
    "words": "92100",
    "words_translated": "75370",
    "words_approved": "138",
    "translated_progress": 81,
    "approved_progress": 0,
    "qa_issues": 243
  },
  {
    "name": "Chinese Traditional",
    "code": "zh-TW",
    "phrases": "9953",
    "translated": "4603",
    "approved": "46",
    "words": "92100",
    "words_translated": "23216",
    "words_approved": "115",
    "translated_progress": 25,
    "approved_progress": 0,
    "qa_issues": 59
  },
  {
    "name": "Czech",
    "code": "cs",
    "phrases": "9953",
    "translated": "1167",
    "approved": "0",
    "words": "92100",
    "words_translated": "3021",
    "words_approved": "0",
    "translated_progress": 3,
    "approved_progress": 0,
    "qa_issues": 248
  },
  {
    "name": "Dutch",
    "code": "nl",
    "phrases": "9953",
    "translated": "2683",
    "approved": "4",
    "words": "92100",
    "words_translated": "9182",
    "words_approved": "61",
    "translated_progress": 9,
    "approved_progress": 0,
    "qa_issues": 760
  },
  {
    "name": "Filipino",
    "code": "fil",
    "phrases": "9953",
    "translated": "7763",
    "approved": "1064",
    "words": "92100",
    "words_translated": "63696",
    "words_approved": "10830",
    "translated_progress": 69,
    "approved_progress": 11,
    "qa_issues": 209
  },
  {
    "name": "French",
    "code": "fr",
    "phrases": "9953",
    "translated": "7185",
    "approved": "39",
    "words": "92100",
    "words_translated": "53952",
    "words_approved": "142",
    "translated_progress": 58,
    "approved_progress": 0,
    "qa_issues": 2082
  },
  {
    "name": "German",
    "code": "de",
    "phrases": "9953",
    "translated": "2878",
    "approved": "35",
    "words": "92100",
    "words_translated": "17962",
    "words_approved": "66",
    "translated_progress": 19,
    "approved_progress": 0,
    "qa_issues": 1098
  },
  {
    "name": "Hebrew",
    "code": "he",
    "phrases": "9953",
    "translated": "216",
    "approved": "0",
    "words": "92100",
    "words_translated": "1508",
    "words_approved": "0",
    "translated_progress": 1,
    "approved_progress": 0,
    "qa_issues": 67
  },
  {
    "name": "Hindi",
    "code": "hi",
    "phrases": "9953",
    "translated": "1385",
    "approved": "6",
    "words": "92100",
    "words_translated": "13488",
    "words_approved": "28",
    "translated_progress": 14,
    "approved_progress": 0,
    "qa_issues": 1292
  },
  {
    "name": "Indonesian",
    "code": "id",
    "phrases": "9953",
    "translated": "7844",
    "approved": "6",
    "words": "92100",
    "words_translated": "64408",
    "words_approved": "62",
    "translated_progress": 69,
    "approved_progress": 0,
    "qa_issues": 4228
  },
  {
    "name": "Italian",
    "code": "it",
    "phrases": "9953",
    "translated": "4782",
    "approved": "3",
    "words": "92100",
    "words_translated": "34813",
    "words_approved": "43",
    "translated_progress": 37,
    "approved_progress": 0,
    "qa_issues": 1743
  },
  {
    "name": "Japanese",
    "code": "ja",
    "phrases": "9953",
    "translated": "8748",
    "approved": "291",
    "words": "92100",
    "words_translated": "74257",
    "words_approved": "1620",
    "translated_progress": 80,
    "approved_progress": 1,
    "qa_issues": 276
  },
  {
    "name": "Korean",
    "code": "ko",
    "phrases": "9953",
    "translated": "4399",
    "approved": "358",
    "words": "92100",
    "words_translated": "36706",
    "words_approved": "3296",
    "translated_progress": 39,
    "approved_progress": 3,
    "qa_issues": 1941
  },
  {
    "name": "Persian",
    "code": "fa",
    "phrases": "9953",
    "translated": "971",
    "approved": "30",
    "words": "92100",
    "words_translated": "4074",
    "words_approved": "54",
    "translated_progress": 4,
    "approved_progress": 0,
    "qa_issues": 39
  },
  {
    "name": "Polish",
    "code": "pl",
    "phrases": "9953",
    "translated": "4099",
    "approved": "851",
    "words": "92100",
    "words_translated": "20244",
    "words_approved": "5995",
    "translated_progress": 21,
    "approved_progress": 6,
    "qa_issues": 900
  },
  {
    "name": "Portuguese, Brazilian",
    "code": "pt-BR",
    "phrases": "9953",
    "translated": "4370",
    "approved": "365",
    "words": "92100",
    "words_translated": "31003",
    "words_approved": "2607",
    "translated_progress": 33,
    "approved_progress": 2,
    "qa_issues": 1259
  },
  {
    "name": "Romanian",
    "code": "ro",
    "phrases": "9953",
    "translated": "399",
    "approved": "0",
    "words": "92100",
    "words_translated": "1851",
    "words_approved": "0",
    "translated_progress": 2,
    "approved_progress": 0,
    "qa_issues": 96
  },
  {
    "name": "Russian",
    "code": "ru",
    "phrases": "9953",
    "translated": "5276",
    "approved": "995",
    "words": "92100",
    "words_translated": "38331",
    "words_approved": "7329",
    "translated_progress": 41,
    "approved_progress": 7,
    "qa_issues": 1578
  },
  {
    "name": "Spanish",
    "code": "es-ES",
    "phrases": "9953",
    "translated": "8669",
    "approved": "254",
    "words": "92100",
    "words_translated": "74524",
    "words_approved": "2104",
    "translated_progress": 80,
    "approved_progress": 2,
    "qa_issues": 3332
  },
  {
    "name": "Tagalog",
    "code": "tl",
    "phrases": "9953",
    "translated": "0",
    "approved": "0",
    "words": "92100",
    "words_translated": "0",
    "words_approved": "0",
    "translated_progress": 0,
    "approved_progress": 0,
    "qa_issues": 0
  },
  {
    "name": "Thai",
    "code": "th",
    "phrases": "9953",
    "translated": "356",
    "approved": "5",
    "words": "92100",
    "words_translated": "1954",
    "words_approved": "62",
    "translated_progress": 2,
    "approved_progress": 0,
    "qa_issues": 101
  },
  {
    "name": "Turkish",
    "code": "tr",
    "phrases": "9953",
    "translated": "7867",
    "approved": "2",
    "words": "92100",
    "words_translated": "64735",
    "words_approved": "2",
    "translated_progress": 70,
    "approved_progress": 0,
    "qa_issues": 3658
  },
  {
    "name": "Ukrainian",
    "code": "uk",
    "phrases": "9953",
    "translated": "4004",
    "approved": "153",
    "words": "92100",
    "words_translated": "24418",
    "words_approved": "711",
    "translated_progress": 26,
    "approved_progress": 0,
    "qa_issues": 1610
  },
  {
    "name": "Vietnamese",
    "code": "vi",
    "phrases": "9953",
    "translated": "1953",
    "approved": "53",
    "words": "92100",
    "words_translated": "9290",
    "words_approved": "170",
    "translated_progress": 10,
    "approved_progress": 0,
    "qa_issues": 535
  }
]