[
  {
    "name": "Arabic",
    "code": "ar",
    "phrases": "10006",
    "translated": "1060",
    "approved": "0",
    "words": "92701",
    "words_translated": "7131",
    "words_approved": "0",
    "translated_progress": 7,
    "approved_progress": 0,
    "qa_issues": 392
  },
  {
    "name": "Bulgarian",
    "code": "bg",
    "phrases": "10006",
    "translated": "2439",
    "approved": "3",
    "words": "92701",
    "words_translated": "13596",
    "words_approved": "6",
    "translated_progress": 14,
    "approved_progress": 0,
    "qa_issues": 701
  },
  {
    "name": "Chinese Simplified",
    "code": "zh-CN",
    "phrases": "10006",
    "translated": "8753",
    "approved": "26",
    "words": "92701",
    "words_translated": "76591",
    "words_approved": "138",
    "translated_progress": 82,
    "approved_progress": 0,
    "qa_issues": 251
  },
  {
    "name": "Chinese Traditional",
    "code": "zh-TW",
    "phrases": "10006",
    "translated": "4616",
    "approved": "46",
    "words": "92701",
    "words_translated": "23341",
    "words_approved": "115",
    "translated_progress": 25,
    "approved_progress": 0,
    "qa_issues": 58
  },
  {
    "name": "Czech",
    "code": "cs",
    "phrases": "10006",
    "translated": "1207",
    "approved": "0",
    "words": "92701",
    "words_translated": "3332",
    "words_approved": "0",
    "translated_progress": 3,
    "approved_progress": 0,
    "qa_issues": 257
  },
  {
    "name": "Dutch",
    "code": "nl",
    "phrases": "10006",
    "translated": "2687",
    "approved": "4",
    "words": "92701",
    "words_translated": "9166",
    "words_approved": "61",
    "translated_progress": 9,
    "approved_progress": 0,
    "qa_issues": 760
  },
  {
    "name": "Filipino",
    "code": "fil",
    "phrases": "10006",
    "translated": "7767",
    "approved": "1064",
    "words": "92701",
    "words_translated": "63675",
    "words_approved": "10830",
    "translated_progress": 68,
    "approved_progress": 11,
    "qa_issues": 210
  },
  {
    "name": "French",
    "code": "fr",
    "phrases": "10006",
    "translated": "7328",
    "approved": "39",
    "words": "92701",
    "words_translated": "55349",
    "words_approved": "142",
    "translated_progress": 59,
    "approved_progress": 0,
    "qa_issues": 2130
  },
  {
    "name": "German",
    "code": "de",
    "phrases": "10006",
    "translated": "2884",
    "approved": "35",
    "words": "92701",
    "words_translated": "18001",
    "words_approved": "66",
    "translated_progress": 19,
    "approved_progress": 0,
    "qa_issues": 1099
  },
  {
    "name": "Hebrew",
    "code": "he",
    "phrases": "10006",
    "translated": "304",
    "approved": "0",
    "words": "92701",
    "words_translated": "2180",
    "words_approved": "0",
    "translated_progress": 2,
    "approved_progress": 0,
    "qa_issues": 98
  },
  {
    "name": "Hindi",
    "code": "hi",
    "phrases": "10006",
    "translated": "1424",
    "approved": "6",
    "words": "92701",
    "words_translated": "13858",
    "words_approved": "28",
    "translated_progress": 14,
    "approved_progress": 0,
    "qa_issues": 1326
  },
  {
    "name": "Indonesian",
    "code": "id",
    "phrases": "10006",
    "translated": "7854",
    "approved": "6",
    "words": "92701",
    "words_translated": "64422",
    "words_approved": "62",
    "translated_progress": 69,
    "approved_progress": 0,
    "qa_issues": 4231
  },
  {
    "name": "Italian",
    "code": "it",
    "phrases": "10006",
    "translated": "4785",
    "approved": "3",
    "words": "92701",
    "words_translated": "34839",
    "words_approved": "43",
    "translated_progress": 37,
    "approved_progress": 0,
    "qa_issues": 1743
  },
  {
    "name": "Japanese",
    "code": "ja",
    "phrases": "10006",
    "translated": "9202",
    "approved": "291",
    "words": "92701",
    "words_translated": "81271",
    "words_approved": "1620",
    "translated_progress": 87,
    "approved_progress": 1,
    "qa_issues": 289
  },
  {
    "name": "Korean",
    "code": "ko",
    "phrases": "10006",
    "translated": "4500",
    "approved": "357",
    "words": "92701",
    "words_translated": "38119",
    "words_approved": "3294",
    "translated_progress": 41,
    "approved_progress": 3,
    "qa_issues": 2008
  },
  {
    "name": "Persian",
    "code": "fa",
    "phrases": "10006",
    "translated": "991",
    "approved": "30",
    "words": "92701",
    "words_translated": "4220",
    "words_approved": "54",
    "translated_progress": 4,
    "approved_progress": 0,
    "qa_issues": 39
  },
  {
    "name": "Polish",
    "code": "pl",
    "phrases": "10006",
    "translated": "4106",
    "approved": "823",
    "words": "92701",
    "words_translated": "20233",
    "words_approved": "5937",
    "translated_progress": 21,
    "approved_progress": 6,
    "qa_issues": 904
  },
  {
    "name": "Portuguese, Brazilian",
    "code": "pt-BR",
    "phrases": "10006",
    "translated": "4403",
    "approved": "365",
    "words": "92701",
    "words_translated": "31186",
    "words_approved": "2607",
    "translated_progress": 33,
    "approved_progress": 2,
    "qa_issues": 1266
  },
  {
    "name": "Romanian",
    "code": "ro",
    "phrases": "10006",
    "translated": "409",
    "approved": "0",
    "words": "92701",
    "words_translated": "1960",
    "words_approved": "0",
    "translated_progress": 2,
    "approved_progress": 0,
    "qa_issues": 100
  },
  {
    "name": "Russian",
    "code": "ru",
    "phrases": "10006",
    "translated": "6564",
    "approved": "993",
    "words": "92701",
    "words_translated": "53580",
    "words_approved": "7306",
    "translated_progress": 57,
    "approved_progress": 7,
    "qa_issues": 2086
  },
  {
    "name": "Spanish",
    "code": "es-ES",
    "phrases": "10006",
    "translated": "8682",
    "approved": "254",
    "words": "92701",
    "words_translated": "74610",
    "words_approved": "2104",
    "translated_progress": 80,
    "approved_progress": 2,
    "qa_issues": 3336
  },
  {
    "name": "Tagalog",
    "code": "tl",
    "phrases": "10006",
    "translated": "0",
    "approved": "0",
    "words": "92701",
    "words_translated": "0",
    "words_approved": "0",
    "translated_progress": 0,
    "approved_progress": 0,
    "qa_issues": 0
  },
  {
    "name": "Thai",
    "code": "th",
    "phrases": "10006",
    "translated": "359",
    "approved": "5",
    "words": "92701",
    "words_translated": "1946",
    "words_approved": "62",
    "translated_progress": 2,
    "approved_progress": 0,
    "qa_issues": 104
  },
  {
    "name": "Turkish",
    "code": "tr",
    "phrases": "10006",
    "translated": "7954",
    "approved": "2",
    "words": "92701",
    "words_translated": "65394",
    "words_approved": "2",
    "translated_progress": 70,
    "approved_progress": 0,
    "qa_issues": 3682
  },
  {
    "name": "Ukrainian",
    "code": "uk",
    "phrases": "10006",
    "translated": "4008",
    "approved": "153",
    "words": "92701",
    "words_translated": "24436",
    "words_approved": "711",
    "translated_progress": 26,
    "approved_progress": 0,
    "qa_issues": 1610
  },
  {
    "name": "Vietnamese",
    "code": "vi",
    "phrases": "10006",
    "translated": "1958",
    "approved": "53",
    "words": "92701",
    "words_translated": "9279",
    "words_approved": "170",
    "translated_progress": 10,
    "approved_progress": 0,
    "qa_issues": 534
  }
]